awips/AlertVizHandler.py
awips/ConfigFileUtil.py
awips/DateTimeConverter.py
awips/NotificationMessage.py
awips/QpidSubscriber.py
awips/RadarCommon.py
awips/ThriftClient.py
awips/TimeUtil.py
awips/UsageArgumentParser.py
awips/UsageOptionParser.py
awips/__init__.py
awips/ignite_password.py
awips/qpidingest.py
awips/tables.py
awips/dataaccess/CombinedTimeQuery.py
awips/dataaccess/DataAccessLayer.py
awips/dataaccess/DataNotificationLayer.py
awips/dataaccess/DataQueue.py
awips/dataaccess/ModelSounding.py
awips/dataaccess/PyData.py
awips/dataaccess/PyGeometryData.py
awips/dataaccess/PyGeometryNotification.py
awips/dataaccess/PyGridData.py
awips/dataaccess/PyGridNotification.py
awips/dataaccess/PyNotification.py
awips/dataaccess/SoundingsSupport.py
awips/dataaccess/ThriftClientRouter.py
awips/dataaccess/__init__.py
awips/gempak/GridDataRetriever.py
awips/gempak/GridInfoRetriever.py
awips/gempak/GridNavRetriever.py
awips/gempak/StationDataRetriever.py
awips/gempak/StationRetriever.py
awips/gempak/TimeRetriever.py
awips/gempak/ncepGribTables.py
awips/gempak/scrape.py
awips/gfe/IFPClient.py
awips/gfe/__init__.py
awips/localization/LocalizationFileManager.py
awips/localization/LocalizationUtil.py
awips/localization/__init__.py
awips/test/Record.py
awips/test/__init__.py
awips/test/testQpidTimeToLive.py
awips/test/dafTests/__init__.py
awips/test/dafTests/baseBufrMosTestCase.py
awips/test/dafTests/baseDafTestCase.py
awips/test/dafTests/baseRadarTestCase.py
awips/test/dafTests/params.py
awips/test/dafTests/testAcars.py
awips/test/dafTests/testAirep.py
awips/test/dafTests/testBinLightning.py
awips/test/dafTests/testBufrMosAvn.py
awips/test/dafTests/testBufrMosEta.py
awips/test/dafTests/testBufrMosGfs.py
awips/test/dafTests/testBufrMosHpc.py
awips/test/dafTests/testBufrMosLamp.py
awips/test/dafTests/testBufrMosMrf.py
awips/test/dafTests/testBufrUa.py
awips/test/dafTests/testClimate.py
awips/test/dafTests/testCombinedTimeQuery.py
awips/test/dafTests/testCommonObsSpatial.py
python_awips-23.1.1.dist-info/licenses/LICENSE
python_awips-23.1.1.dist-info/METADATA
python_awips-23.1.1.dist-info/WHEEL
python_awips-23.1.1.dist-info/top_level.txt
python_awips-23.1.1.dist-info/RECORD
