Metadata-Version: 2.4
Name: python-awips
Version: 23.1.1
Summary: A framework for requesting AWIPS meteorological datasets from an EDEX server
Author-email: NSF Unidata <support-awips@ucar.edu>
License: Copyright (c) 2017, Unidata Python AWIPS Developers.
Requires-Python: >=3.8
License-File: LICENSE
Requires-Dist: numpy
Provides-Extra: cdm
Requires-Dist: pyproj>=1.9.4; extra == "cdm"
Provides-Extra: dev
Requires-Dist: ipython[all]>=3.1; extra == "dev"
Provides-Extra: doc
Requires-Dist: sphinx>=1.4; extra == "doc"
Requires-Dist: sphinx-gallery; extra == "doc"
Requires-Dist: doc8; extra == "doc"
Provides-Extra: examples
Requires-Dist: cartopy>=0.13.1; extra == "examples"
Requires-Dist: metpy>=0.4.0; extra == "examples"
Dynamic: license-file
